RC2/__init__.py
RC2/cli.py
RC2/common.py
RC2/core.py
RC2/data_readers.py
RC2/piv.py
RC2/plotting.py
RC2/vtk.py
rc2SFB-0.0.13.dist-info/METADATA
rc2SFB-0.0.13.dist-info/WHEEL
rc2SFB-0.0.13.dist-info/top_level.txt
rc2SFB-0.0.13.dist-info/RECORD
