Metadata-Version: 2.1
Name: rc2SFB
Version: 0.0.13
Summary: Tools to read, scale and plot RC2 PIV and OF data  
Home-page: https://github.com/XXXXXXXXXX/XXX
Author: Hakan Demir
Author-email: h.demir@ruhr-uni-bochum.de
License: UNKNOWN
Platform: UNKNOWN
Classifier: Topic :: Scientific/Engineering
